__init__.py
socks.py
ssl_checker.py
python_ssl_checker-1.1.0.dist-info/LICENSE
python_ssl_checker-1.1.0.dist-info/METADATA
python_ssl_checker-1.1.0.dist-info/WHEEL
python_ssl_checker-1.1.0.dist-info/top_level.txt
python_ssl_checker-1.1.0.dist-info/RECORD
