Metadata-Version: 2.1
Name: python-ssl-checker
Version: 1.1.0
Summary: Python script that collects SSL/TLS information from hosts
Author-email: Narbeh Arakil <narbeh@protonmail.com>
License: GNU GENERAL PUBLIC LICENSE
Keywords: ssl,tls,certificate,checker
Classifier: License :: OSI Approved :: MIT License
Classifier: Programming Language :: Python
Classifier: Programming Language :: Python :: 3
Requires-Python: >=3.6
License-File: LICENSE
Requires-Dist: pyopenssl
Requires-Dist: json2html
